raspcuterie/__init__.py
raspcuterie/app.py
raspcuterie/conftest.py
raspcuterie/gpio.py
raspcuterie/utils.py
raspcuterie/wsgi.py
raspcuterie/cli/__init__.py
raspcuterie/cli/config.yaml
raspcuterie/cli/cron.py
raspcuterie/cli/fake.py
raspcuterie/cli/install.py
raspcuterie/cli/tests/__init__.py
raspcuterie/cli/tests/conftest.py
raspcuterie/cli/tests/test_cli.py
raspcuterie/cli/tests/test_cron.py
raspcuterie/cli/tests/test_fake.py
raspcuterie/cli/tests/test_install.py
raspcuterie/config/__init__.py
raspcuterie/config/tests/__init__.py
raspcuterie/config/tests/test_parse_config.py
raspcuterie/dashboard/__init__.py
raspcuterie/dashboard/api.py
raspcuterie/dashboard/dashboard.py
raspcuterie/dashboard/templates/dashboard.html
raspcuterie/dashboard/tests/__init__.py
raspcuterie/dashboard/tests/test_api.py
raspcuterie/dashboard/tests/test_dashboard.py
raspcuterie/db/__init__.py
raspcuterie/devices/__init__.py
raspcuterie/devices/control.py
raspcuterie/devices/input/__init__.py
raspcuterie/devices/input/am2302.py
raspcuterie/devices/input/sinus.py
raspcuterie/devices/input/hx711/__init__.py
raspcuterie/devices/input/hx711/calibration.py
raspcuterie/devices/input/hx711/display.py
raspcuterie/devices/output/__init__.py
raspcuterie/devices/output/relay.py
raspcuterie/devices/output/tests/__init__.py
raspcuterie/devices/output/tests/test_db_relay.py
raspcuterie/devices/output/tests/test_relay.py
raspcuterie/devices/tests/__init__.py
raspcuterie/devices/tests/test_control.py
raspcuterie-0.2.0.dist-info/METADATA
raspcuterie-0.2.0.dist-info/WHEEL
raspcuterie-0.2.0.dist-info/entry_points.txt
raspcuterie-0.2.0.dist-info/top_level.txt
raspcuterie-0.2.0.dist-info/RECORD
