Metadata-Version: 2.1
Name: raspcuterie
Version: 0.2.0
Summary: Charcuterie dashboard and controller for the Raspberry PI
Home-page: https://github.com/foarsitter/raspcuterie
License: MIT
Platform: UNKNOWN
Requires-Dist: Flask (==1.1.2)
Requires-Dist: Click (==7.1.2)
Requires-Dist: pyyaml (==5.4)
Requires-Dist: adafruit-circuitpython-dht (==3.5.1)
Requires-Dist: rpi.gpio (==0.7.0)
